[
    {
        "origin_chapter": "bofm/ether/11",
        "noteId": "note1a",
        "content": "prophets",
        "refs": ["bofm:ether:7_p23#p23", "bofm:ether:9_p28#p28"]
    },
    {
        "origin_chapter": "bofm/ether/11",
        "noteId": "note2a",
        "content": "rejected",
        "refs": ["tg:prophets-rejection-of"]
    },
    {
        "origin_chapter": "bofm/ether/11",
        "noteId": "note5a",
        "content": "death",
        "refs": ["tg:persecution"]
    },
    {
        "origin_chapter": "bofm/ether/11",
        "noteId": "note6a",
        "content": "heaps",
        "refs": ["bofm:omni:1_p22#p22", "bofm:ether:14_p21#p21"]
    },
    {
        "origin_chapter": "bofm/ether/11",
        "noteId": "note7a",
        "content": "contentions",
        "refs": ["tg:contention"]
    },
    {
        "origin_chapter": "bofm/ether/11",
        "noteId": "note8a",
        "content": "mercy",
        "refs": ["tg:mercy"]
    },
    {
        "origin_chapter": "bofm/ether/11",
        "noteId": "note9a",
        "content": "captivity",
        "refs": ["bofm:ether:10_p30#p30", "bofm:ether:11_p18-p19#p18"]
    },
    {
        "origin_chapter": "bofm/ether/11",
        "noteId": "note12a",
        "content": "destroy",
        "refs": ["bofm:ether:12_p3#p3"]
    },
    {
        "origin_chapter": "bofm/ether/11",
        "noteId": "note13a",
        "content": "hearken",
        "refs": ["ot:jer:44_p16#p16", "bofm:mosiah:16_p2#p2"]
    },
    {
        "origin_chapter": "bofm/ether/11",
        "noteId": "note13b",
        "content": "mourned",
        "refs": ["tg:mourning"]
    },
    {
        "origin_chapter": "bofm/ether/11",
        "noteId": "note15a",
        "content": "rebellion",
        "refs": ["tg:rebellion"]
    },
    {
        "origin_chapter": "bofm/ether/11",
        "noteId": "note15b",
        "content": "combination",
        "refs": ["tg:secret-combinations"]
    },
    {
        "origin_chapter": "bofm/ether/11",
        "noteId": "note18a",
        "content": "captivity",
        "refs": ["bofm:ether:11_p9#p9"]
    },
    {
        "origin_chapter": "bofm/ether/11",
        "noteId": "note20a",
        "content": "judgment",
        "refs": ["tg:judgment"]
    },
    {
        "origin_chapter": "bofm/ether/11",
        "noteId": "note21a",
        "content": "another",
        "refs": ["bofm:omni:1_p21#p21", "bofm:ether:13_p20-p21#p21"]
    },
    {
        "origin_chapter": "bofm/ether/11",
        "noteId": "note21b",
        "content": "land",
        "refs": ["ot:deut:29_p28#p28"]
    },
    {
        "origin_chapter": "bofm/ether/11",
        "noteId": "note22a",
        "content": "reject",
        "refs": ["tg:prophets-rejection-of"]
    },
    {
        "origin_chapter": "bofm/ether/11",
        "noteId": "note22b",
        "content": "secret society",
        "refs": ["tg:secret-combinations"]
    },
    {
        "origin_chapter": "bofm/ether/11",
        "noteId": "note23a",
        "content": "Ether",
        "refs": [
            "bofm:ether:1_p6#p6",
            "bofm:ether:12_p2#p2",
            "bofm:ether:15_p33-p34#p34"
        ]
    }
]
