[
    {
        "origin_chapter": "bofm/alma/34",
        "noteId": "note1a",
        "content": "Amulek",
        "refs": ["bofm:alma:8_p21#p21", "bofm:alma:31_p32#p32"]
    },
    {
        "origin_chapter": "bofm/alma/34",
        "noteId": "note2a",
        "content": "these things",
        "refs": ["bofm:alma:16_p13-p21#p15"]
    },
    {
        "origin_chapter": "bofm/alma/34",
        "noteId": "note3a",
        "content": "what",
        "refs": ["bofm:alma:32_p5#p5"]
    },
    {
        "origin_chapter": "bofm/alma/34",
        "noteId": "note4a",
        "content": "plant",
        "refs": ["bofm:alma:33_p23#p23"]
    },
    {
        "origin_chapter": "bofm/alma/34",
        "noteId": "note5a",
        "content": "no",
        "refs": [
            "bofm:jacob:7_p2,9#p2",
            "bofm:alma:30_p12,22#p12",
            "bofm:alma:31_p16,29#p16"
        ]
    },
    {
        "origin_chapter": "bofm/alma/34",
        "noteId": "note6a",
        "content": "word",
        "refs": ["nt:john:1_p1,14#p14"]
    },
    {
        "origin_chapter": "bofm/alma/34",
        "noteId": "note7a",
        "content": "Zenos",
        "refs": ["bofm:alma:33_p13#p13", "bofm:hel:8_p19#p19"]
    },
    {
        "origin_chapter": "bofm/alma/34",
        "noteId": "note7b",
        "content": "Zenock",
        "refs": ["bofm:alma:33_p15#p15", "bofm:hel:8_p19-p20#p20"]
    },
    {
        "origin_chapter": "bofm/alma/34",
        "noteId": "note7c",
        "content": "Moses",
        "refs": ["bofm:alma:33_p19#p19"]
    },
    {
        "origin_chapter": "bofm/alma/34",
        "noteId": "note8a",
        "content": "testify",
        "refs": ["tg:testimony", "tg:witness"]
    },
    {
        "origin_chapter": "bofm/alma/34",
        "noteId": "note8b",
        "content": "transgressions",
        "refs": ["tg:jesus-christ-redeemer"]
    },
    {
        "origin_chapter": "bofm/alma/34",
        "noteId": "note8c",
        "content": "atone",
        "refs": ["tg:jesus-christ-atonement-through"]
    },
    {
        "origin_chapter": "bofm/alma/34",
        "noteId": "note9a",
        "content": "atonement",
        "refs": [
            "bofm:2-ne:2_p10#p10",
            "bofm:2-ne:9_p7-p9#p7",
            "bofm:alma:22_p14#p14",
            "bofm:alma:33_p22#p22"
        ]
    },
    {
        "origin_chapter": "bofm/alma/34",
        "noteId": "note9b",
        "content": "plan",
        "refs": [
            "bofm:alma:12_p22-p33#p26",
            "bofm:alma:42_p6-p28#p8",
            "pgp:moses:6_p62#p62"
        ]
    },
    {
        "origin_chapter": "bofm/alma/34",
        "noteId": "note9c",
        "content": "fallen",
        "refs": ["tg:fall-of-man"]
    },
    {
        "origin_chapter": "bofm/alma/34",
        "noteId": "note10a",
        "content": "sacrifice",
        "refs": ["ot:1-chr:6_p49#p49", "pgp:moses:5_p6-p7#p7"]
    },
    {
        "origin_chapter": "bofm/alma/34",
        "noteId": "note10b",
        "content": "sacrifice",
        "refs": ["tg:blood-symbolism-of"]
    },
    {
        "origin_chapter": "bofm/alma/34",
        "noteId": "note10c",
        "content": "infinite",
        "refs": ["bofm:2-ne:9_p7#p7"]
    },
    {
        "origin_chapter": "bofm/alma/34",
        "noteId": "note10d",
        "content": "eternal",
        "refs": ["ot:isa:45_p17#p17", "nt:heb:5_p9#p9"]
    },
    {
        "origin_chapter": "bofm/alma/34",
        "noteId": "note10e",
        "content": "sacrifice",
        "refs": ["tg:sacrifice"]
    },
    {
        "origin_chapter": "bofm/alma/34",
        "noteId": "note11a",
        "content": "just",
        "refs": ["ot:deut:24_p16#p16", "bofm:mosiah:29_p25#p25"]
    },
    {
        "origin_chapter": "bofm/alma/34",
        "noteId": "note12a",
        "content": "life",
        "refs": ["tg:blood-shedding-of", "tg:life-sanctity-of"]
    },
    {
        "origin_chapter": "bofm/alma/34",
        "noteId": "note12b",
        "content": "murdered",
        "refs": ["tg:capital-punishment", "tg:murder"]
    },
    {
        "origin_chapter": "bofm/alma/34",
        "noteId": "note13a",
        "content": "stop",
        "refs": ["bofm:3-ne:9_p19#p19"]
    },
    {
        "origin_chapter": "bofm/alma/34",
        "noteId": "note13b",
        "content": "blood",
        "refs": ["tg:blood-symbolism-of"]
    },
    {
        "origin_chapter": "bofm/alma/34",
        "noteId": "note13c",
        "content": "law",
        "refs": ["bofm:3-ne:1_p24#p24", "bofm:3-ne:15_p5#p5"]
    },
    {
        "origin_chapter": "bofm/alma/34",
        "noteId": "note14a",
        "content": "meaning",
        "refs": [
            "bofm:2-ne:25_p24#p24",
            "bofm:jarom:1_p5#p5",
            "bofm:mosiah:2_p3#p3",
            "bofm:alma:30_p3#p3"
        ]
    },
    {
        "origin_chapter": "bofm/alma/34",
        "noteId": "note14b",
        "content": "law",
        "refs": ["tg:law-of-moses"]
    },
    {
        "origin_chapter": "bofm/alma/34",
        "noteId": "note14c",
        "content": "pointing",
        "refs": ["tg:jesus-christ-types-of-in-anticipation"]
    },
    {
        "origin_chapter": "bofm/alma/34",
        "noteId": "note14d",
        "content": "sacrifice",
        "refs": ["ot:ex:12_p1-p30#p21"]
    },
    {
        "origin_chapter": "bofm/alma/34",
        "noteId": "note14e",
        "content": "sacrifice",
        "refs": ["dnc:138_p35#p35"]
    },
    {
        "origin_chapter": "bofm/alma/34",
        "noteId": "note14f",
        "content": "infinite",
        "refs": ["dnc:20_p17,28#p17"]
    },
    {
        "origin_chapter": "bofm/alma/34",
        "noteId": "note15a",
        "content": "salvation",
        "refs": ["tg:salvation"]
    },
    {
        "origin_chapter": "bofm/alma/34",
        "noteId": "note16a",
        "content": "mercy",
        "refs": ["tg:mercy"]
    },
    {
        "origin_chapter": "bofm/alma/34",
        "noteId": "note16b",
        "content": "justice",
        "refs": ["tg:god-justice-of"]
    },
    {
        "origin_chapter": "bofm/alma/34",
        "noteId": "note16c",
        "content": "justice",
        "refs": ["bofm:mosiah:15_p27#p27", "bofm:alma:12_p32#p32"]
    },
    {
        "origin_chapter": "bofm/alma/34",
        "noteId": "note16d",
        "content": "plan",
        "refs": ["tg:salvation-plan-of"]
    },
    {
        "origin_chapter": "bofm/alma/34",
        "noteId": "note16e",
        "content": "redemption",
        "refs": ["tg:redemption"]
    },
    {
        "origin_chapter": "bofm/alma/34",
        "noteId": "note17a",
        "content": "faith",
        "refs": ["tg:faith"]
    },
    {
        "origin_chapter": "bofm/alma/34",
        "noteId": "note17b",
        "content": "call",
        "refs": ["tg:god-access-to", "tg:prayer"]
    },
    {
        "origin_chapter": "bofm/alma/34",
        "noteId": "note18a",
        "content": "mighty",
        "refs": ["nt:heb:7_p24-p25#p25"]
    },
    {
        "origin_chapter": "bofm/alma/34",
        "noteId": "note19a",
        "content": "prayer",
        "refs": ["tg:prayer"]
    },
    {
        "origin_chapter": "bofm/alma/34",
        "noteId": "note20a",
        "content": "fields",
        "refs": ["bofm:alma:33_p4-p5#p5"]
    },
    {
        "origin_chapter": "bofm/alma/34",
        "noteId": "note21a",
        "content": "Cry",
        "refs": ["ot:ps:5_p1-p3#p3", "ot:dan:6_p10#p10", "bofm:3-ne:18_p21#p21"]
    },
    {
        "origin_chapter": "bofm/alma/34",
        "noteId": "note22a",
        "content": "enemies",
        "refs": ["tg:enemies"]
    },
    {
        "origin_chapter": "bofm/alma/34",
        "noteId": "note23a",
        "content": "cry",
        "refs": ["bofm:3-ne:18_p15,18#p15"]
    },
    {
        "origin_chapter": "bofm/alma/34",
        "noteId": "note23b",
        "content": "devil",
        "refs": ["tg:devil"]
    },
    {
        "origin_chapter": "bofm/alma/34",
        "noteId": "note23c",
        "content": "righteousness",
        "refs": ["tg:righteousness"]
    },
    {
        "origin_chapter": "bofm/alma/34",
        "noteId": "note26a",
        "content": "pour out",
        "refs": ["ot:1-sam:1_p15#p15", "bofm:enos:1_p9#p9"]
    },
    {
        "origin_chapter": "bofm/alma/34",
        "noteId": "note26b",
        "content": "closets",
        "refs": ["nt:matt:6_p5-p6#p6", "bofm:alma:33_p4-p11#p7"]
    },
    {
        "origin_chapter": "bofm/alma/34",
        "noteId": "note27a",
        "content": "hearts",
        "refs": ["tg:heart"]
    },
    {
        "origin_chapter": "bofm/alma/34",
        "noteId": "note27b",
        "content": "full",
        "refs": ["tg:meditation"]
    },
    {
        "origin_chapter": "bofm/alma/34",
        "noteId": "note27c",
        "content": "welfare",
        "refs": ["bofm:2-ne:32_p9#p9", "tg:welfare"]
    },
    {
        "origin_chapter": "bofm/alma/34",
        "noteId": "note27d",
        "content": "those",
        "refs": ["dnc:108_p7#p7"]
    },
    {
        "origin_chapter": "bofm/alma/34",
        "noteId": "note28a",
        "content": "turn away",
        "refs": ["tg:apathy"]
    },
    {
        "origin_chapter": "bofm/alma/34",
        "noteId": "note28b",
        "content": "needy",
        "refs": ["tg:poor"]
    },
    {
        "origin_chapter": "bofm/alma/34",
        "noteId": "note28c",
        "content": "naked",
        "refs": ["ot:ezek:18_p5-p9#p7"]
    },
    {
        "origin_chapter": "bofm/alma/34",
        "noteId": "note28d",
        "content": "impart",
        "refs": ["tg:almsgiving", "tg:good-works"]
    },
    {
        "origin_chapter": "bofm/alma/34",
        "noteId": "note28e",
        "content": "prayer",
        "refs": ["ot:ezek:33_p31#p31", "nt:matt:15_p7-p8#p8"]
    },
    {
        "origin_chapter": "bofm/alma/34",
        "noteId": "note28f",
        "content": "vain",
        "refs": ["ot:isa:58_p3#p3", "bofm:moro:7_p6-p8#p6"]
    },
    {
        "origin_chapter": "bofm/alma/34",
        "noteId": "note28g",
        "content": "hypocrites",
        "refs": ["tg:hypocrisy"]
    },
    {
        "origin_chapter": "bofm/alma/34",
        "noteId": "note29a",
        "content": "charitable",
        "refs": ["tg:charity", "tg:generosity"]
    },
    {
        "origin_chapter": "bofm/alma/34",
        "noteId": "note30a",
        "content": "received",
        "refs": ["tg:witness"]
    },
    {
        "origin_chapter": "bofm/alma/34",
        "noteId": "note30b",
        "content": "fruit",
        "refs": ["nt:matt:3_p8#p8", "bofm:alma:13_p13#p13"]
    },
    {
        "origin_chapter": "bofm/alma/34",
        "noteId": "note31a",
        "content": "harden",
        "refs": ["tg:self-mastery"]
    },
    {
        "origin_chapter": "bofm/alma/34",
        "noteId": "note31b",
        "content": "day",
        "refs": ["nt:rom:13_p11-p12#p12"]
    },
    {
        "origin_chapter": "bofm/alma/34",
        "noteId": "note31c",
        "content": "salvation",
        "refs": ["nt:matt:11_p20#p20", "bofm:3-ne:9_p3#p3", "dnc:84_p114#p114"]
    },
    {
        "origin_chapter": "bofm/alma/34",
        "noteId": "note31d",
        "content": "harden",
        "refs": ["tg:hardheartedness"]
    },
    {
        "origin_chapter": "bofm/alma/34",
        "noteId": "note32a",
        "content": "life",
        "refs": ["tg:mortality"]
    },
    {
        "origin_chapter": "bofm/alma/34",
        "noteId": "note32b",
        "content": "prepare",
        "refs": [
            "nt:2-cor:6_p2#p2",
            "bofm:2-ne:2_p21#p21",
            "bofm:alma:12_p24#p24",
            "bofm:alma:42_p4-p6#p4",
            "tg:self-mastery"
        ]
    },
    {
        "origin_chapter": "bofm/alma/34",
        "noteId": "note32c",
        "content": "this",
        "refs": ["dnc:138_p57#p57"]
    },
    {
        "origin_chapter": "bofm/alma/34",
        "noteId": "note32d",
        "content": "labors",
        "refs": ["tg:good-works", "tg:industry"]
    },
    {
        "origin_chapter": "bofm/alma/34",
        "noteId": "note33a",
        "content": "witnesses",
        "refs": ["tg:witness"]
    },
    {
        "origin_chapter": "bofm/alma/34",
        "noteId": "note33b",
        "content": "procrastinate",
        "refs": [
            "ot:job:27_p8#p8",
            "bofm:hel:13_p38#p38",
            "dnc:45_p2#p2",
            "tg:apathy",
            "tg:idleness",
            "tg:procrastination"
        ]
    },
    {
        "origin_chapter": "bofm/alma/34",
        "noteId": "note33c",
        "content": "repentance",
        "refs": ["tg:repent"]
    },
    {
        "origin_chapter": "bofm/alma/34",
        "noteId": "note33d",
        "content": "night",
        "refs": ["ot:eccl:9_p10#p10", "nt:john:9_p4#p4"]
    },
    {
        "origin_chapter": "bofm/alma/34",
        "noteId": "note33e",
        "content": "darkness",
        "refs": ["tg:darkness-spiritual"]
    },
    {
        "origin_chapter": "bofm/alma/34",
        "noteId": "note34a",
        "content": "crisis",
        "refs": ["bofm:alma:40_p13-p14#p14", "bofm:ether:9_p34#p34"]
    },
    {
        "origin_chapter": "bofm/alma/34",
        "noteId": "note34b",
        "content": "possess",
        "refs": ["nt:rom:6_p14-p18#p16"]
    },
    {
        "origin_chapter": "bofm/alma/34",
        "noteId": "note35a",
        "content": "subjected",
        "refs": ["bofm:2-ne:28_p19-p23#p19"]
    },
    {
        "origin_chapter": "bofm/alma/34",
        "noteId": "note35b",
        "content": "seal",
        "refs": [
            "bofm:2-ne:9_p9#p9",
            "bofm:3-ne:2_p10#p10",
            "tg:devil",
            "tg:sealing"
        ]
    },
    {
        "origin_chapter": "bofm/alma/34",
        "noteId": "note36a",
        "content": "unholy",
        "refs": [
            "bofm:mosiah:2_p37#p37",
            "bofm:alma:7_p21#p21",
            "bofm:hel:4_p24#p24",
            "tg:cleanliness"
        ]
    },
    {
        "origin_chapter": "bofm/alma/34",
        "noteId": "note36b",
        "content": "hearts",
        "refs": ["dnc:130_p3#p3"]
    },
    {
        "origin_chapter": "bofm/alma/34",
        "noteId": "note36c",
        "content": "righteous",
        "refs": ["tg:righteousness"]
    },
    {
        "origin_chapter": "bofm/alma/34",
        "noteId": "note36d",
        "content": "blood",
        "refs": ["nt:rev:12_p11#p11"]
    },
    {
        "origin_chapter": "bofm/alma/34",
        "noteId": "note37a",
        "content": "work",
        "refs": ["nt:philip:2_p12-p16#p12"]
    },
    {
        "origin_chapter": "bofm/alma/34",
        "noteId": "note38a",
        "content": "contend",
        "refs": ["tg:holy-ghost-loss-of"]
    },
    {
        "origin_chapter": "bofm/alma/34",
        "noteId": "note38b",
        "content": "name",
        "refs": [
            "bofm:mosiah:5_p8#p8",
            "bofm:alma:5_p38#p38",
            "tg:jesus-christ-taking-the-name-of"
        ]
    },
    {
        "origin_chapter": "bofm/alma/34",
        "noteId": "note38c",
        "content": "worship",
        "refs": ["tg:worship"]
    },
    {
        "origin_chapter": "bofm/alma/34",
        "noteId": "note38d",
        "content": "thanksgiving",
        "refs": ["ot:ps:69_p30-p31#p30", "dnc:46_p7#p7", "tg:thanksgiving"]
    },
    {
        "origin_chapter": "bofm/alma/34",
        "noteId": "note38e",
        "content": "mercies",
        "refs": ["ot:gen:32_p10#p10", "bofm:1-ne:1_p20#p20", "dnc:46_p15#p15"]
    },
    {
        "origin_chapter": "bofm/alma/34",
        "noteId": "note39a",
        "content": "exhort",
        "refs": ["nt:heb:3_p13#p13"]
    },
    {
        "origin_chapter": "bofm/alma/34",
        "noteId": "note39b",
        "content": "watchful",
        "refs": ["tg:watch"]
    },
    {
        "origin_chapter": "bofm/alma/34",
        "noteId": "note39c",
        "content": "temptations",
        "refs": ["tg:temptation"]
    },
    {
        "origin_chapter": "bofm/alma/34",
        "noteId": "note39d",
        "content": "no",
        "refs": ["bofm:alma:30_p60#p60"]
    },
    {
        "origin_chapter": "bofm/alma/34",
        "noteId": "note40a",
        "content": "patience",
        "refs": ["tg:patience", "tg:steadfastness"]
    },
    {
        "origin_chapter": "bofm/alma/34",
        "noteId": "note40b",
        "content": "afflictions",
        "refs": ["tg:affliction"]
    },
    {
        "origin_chapter": "bofm/alma/34",
        "noteId": "note40c",
        "content": "revile",
        "refs": ["tg:reviling"]
    },
    {
        "origin_chapter": "bofm/alma/34",
        "noteId": "note40d",
        "content": "exceeding",
        "refs": ["bofm:alma:32_p3#p3"]
    },
    {
        "origin_chapter": "bofm/alma/34",
        "noteId": "note41a",
        "content": "patience",
        "refs": ["tg:patience"]
    },
    {
        "origin_chapter": "bofm/alma/34",
        "noteId": "note41b",
        "content": "afflictions",
        "refs": ["ot:job:23_p2-p5#p2"]
    }
]
