[
    {
        "origin_chapter": "bofm/2-ne/10",
        "noteId": "note1a",
        "content": "branch",
        "refs": [
            "bofm:1-ne:15_p12-p20#p12",
            "bofm:2-ne:3_p5#p5",
            "bofm:jacob:5_p43-p45#p45",
            "bofm:alma:46_p24-p25#p24"
        ]
    },
    {
        "origin_chapter": "bofm/2-ne/10",
        "noteId": "note2a",
        "content": "promises",
        "refs": [
            "bofm:1-ne:22_p8-p12#p8",
            "bofm:3-ne:5_p21-p26#p23",
            "bofm:3-ne:21_p4-p29#p7",
            "tg:promise"
        ]
    },
    {
        "origin_chapter": "bofm/2-ne/10",
        "noteId": "note2b",
        "content": "unbelief",
        "refs": ["tg:doubt"]
    },
    {
        "origin_chapter": "bofm/2-ne/10",
        "noteId": "note2c",
        "content": "restored",
        "refs": ["tg:restoration-of-the-gospel"]
    },
    {
        "origin_chapter": "bofm/2-ne/10",
        "noteId": "note3a",
        "content": "angel",
        "refs": [
            "bofm:2-ne:2_p4#p4",
            "bofm:2-ne:11_p3#p3",
            "bofm:2-ne:25_p19#p19",
            "bofm:jacob:7_p5#p5",
            "bofm:moro:7_p22#p22"
        ]
    },
    {
        "origin_chapter": "bofm/2-ne/10",
        "noteId": "note3b",
        "content": "come",
        "refs": ["tg:jesus-christ-prophecies-about"]
    },
    {
        "origin_chapter": "bofm/2-ne/10",
        "noteId": "note3c",
        "content": "Jews",
        "refs": ["tg:israel-judah-people-of"]
    },
    {
        "origin_chapter": "bofm/2-ne/10",
        "noteId": "note3d",
        "content": "crucify",
        "refs": [
            "nt:luke:18_p31#p31",
            "bofm:1-ne:11_p33#p33",
            "bofm:mosiah:3_p9-p10#p9"
        ]
    },
    {
        "origin_chapter": "bofm/2-ne/10",
        "noteId": "note3e",
        "content": "crucify",
        "refs": [
            "nt:matt:27_p22#p22",
            "nt:luke:22_p2#p2",
            "nt:luke:23_p20-p24#p23"
        ]
    },
    {
        "origin_chapter": "bofm/2-ne/10",
        "noteId": "note3f",
        "content": "God",
        "refs": ["bofm:1-ne:19_p7,10#p10", "bofm:2-ne:26_p12#p12"]
    },
    {
        "origin_chapter": "bofm/2-ne/10",
        "noteId": "note4a",
        "content": "miracles",
        "refs": ["tg:miracle"]
    },
    {
        "origin_chapter": "bofm/2-ne/10",
        "noteId": "note5a",
        "content": "priestcrafts",
        "refs": [
            "nt:matt:27_p11-p26#p20",
            "nt:luke:22_p2#p2",
            "nt:john:11_p47-p53#p47",
            "tg:apostasy-of-israel",
            "tg:priestcraft"
        ]
    },
    {
        "origin_chapter": "bofm/2-ne/10",
        "noteId": "note5b",
        "content": "stiffen",
        "refs": ["tg:stiffnecked"]
    },
    {
        "origin_chapter": "bofm/2-ne/10",
        "noteId": "note5c",
        "content": "crucified",
        "refs": ["tg:jesus-christ-crucifixion-of"]
    },
    {
        "origin_chapter": "bofm/2-ne/10",
        "noteId": "note6a",
        "content": "pestilences",
        "refs": ["tg:plague"]
    },
    {
        "origin_chapter": "bofm/2-ne/10",
        "noteId": "note6b",
        "content": "scattered",
        "refs": [
            "bofm:1-ne:19_p13-p14#p14",
            "bofm:2-ne:25_p15#p15",
            "tg:israel-bondage-of-in-other-lands"
        ]
    },
    {
        "origin_chapter": "bofm/2-ne/10",
        "noteId": "note7a",
        "content": "Lord God",
        "refs": ["tg:jesus-christ-lord"]
    },
    {
        "origin_chapter": "bofm/2-ne/10",
        "noteId": "note7b",
        "content": "When",
        "refs": ["bofm:2-ne:9_p1-p2#p2", "bofm:2-ne:25_p16-p17#p16"]
    },
    {
        "origin_chapter": "bofm/2-ne/10",
        "noteId": "note7c",
        "content": "restored",
        "refs": ["ot:gen:49_p10#p10", "tg:israel-restoration-of"]
    },
    {
        "origin_chapter": "bofm/2-ne/10",
        "noteId": "note7d",
        "content": "lands",
        "refs": ["tg:lands-of-inheritance"]
    },
    {
        "origin_chapter": "bofm/2-ne/10",
        "noteId": "note8a",
        "content": "gathered",
        "refs": ["tg:israel-gathering-of"]
    },
    {
        "origin_chapter": "bofm/2-ne/10",
        "noteId": "note8b",
        "content": "isles",
        "refs": [
            "ot:isa:51_p5#p5",
            "bofm:1-ne:22_p4#p4",
            "bofm:2-ne:29_p7#p7",
            "dnc:133_p8#p8"
        ]
    },
    {
        "origin_chapter": "bofm/2-ne/10",
        "noteId": "note8c",
        "content": "carrying",
        "refs": [
            "ot:isa:11_p14#p14",
            "bofm:1-ne:21_p22#p22",
            "bofm:1-ne:22_p8#p8"
        ]
    },
    {
        "origin_chapter": "bofm/2-ne/10",
        "noteId": "note9a",
        "content": "Yea",
        "refs": ["ot:isa:49_p22-p23#p22", "bofm:2-ne:6_p6#p6"]
    },
    {
        "origin_chapter": "bofm/2-ne/10",
        "noteId": "note9b",
        "content": "promises",
        "refs": [
            "bofm:1-ne:22_p1-p9#p8",
            "bofm:alma:9_p24#p24",
            "dnc:3_p20#p20"
        ]
    },
    {
        "origin_chapter": "bofm/2-ne/10",
        "noteId": "note10a",
        "content": "Gentiles",
        "refs": ["bofm:2-ne:6_p12#p12", "bofm:3-ne:16_p4-p7#p6"]
    },
    {
        "origin_chapter": "bofm/2-ne/10",
        "noteId": "note11a",
        "content": "liberty",
        "refs": ["tg:liberty"]
    },
    {
        "origin_chapter": "bofm/2-ne/10",
        "noteId": "note11b",
        "content": "kings",
        "refs": ["bofm:2-ne:1_p7#p7", "bofm:mosiah:29_p32#p32"]
    },
    {
        "origin_chapter": "bofm/2-ne/10",
        "noteId": "note12a",
        "content": "against",
        "refs": ["bofm:1-ne:13_p19#p19"]
    },
    {
        "origin_chapter": "bofm/2-ne/10",
        "noteId": "note13a",
        "content": "fighteth",
        "refs": ["bofm:1-ne:22_p14,19#p14"]
    },
    {
        "origin_chapter": "bofm/2-ne/10",
        "noteId": "note13b",
        "content": "perish",
        "refs": ["ot:isa:60_p12#p12"]
    },
    {
        "origin_chapter": "bofm/2-ne/10",
        "noteId": "note14a",
        "content": "king",
        "refs": ["tg:kings-earthly"]
    },
    {
        "origin_chapter": "bofm/2-ne/10",
        "noteId": "note14b",
        "content": "king",
        "refs": [
            "ot:josh:2_p11#p11",
            "ot:ps:44_p4#p4",
            "nt:matt:2_p2#p2",
            "bofm:alma:5_p50#p50",
            "dnc:20_p17#p17",
            "dnc:38_p21-p22#p21",
            "dnc:128_p22-p23#p22",
            "pgp:moses:7_p53#p53"
        ]
    },
    {
        "origin_chapter": "bofm/2-ne/10",
        "noteId": "note14c",
        "content": "light",
        "refs": ["tg:jesus-christ-light-of-the-world"]
    },
    {
        "origin_chapter": "bofm/2-ne/10",
        "noteId": "note15a",
        "content": "covenants",
        "refs": ["tg:abrahamic-covenant", "tg:covenants"]
    },
    {
        "origin_chapter": "bofm/2-ne/10",
        "noteId": "note15b",
        "content": "secret",
        "refs": [
            "ot:lev:19_p26#p26",
            "bofm:hel:3_p23#p23",
            "bofm:hel:7_p4-p5,21,25#p25",
            "tg:secret-combinations"
        ]
    },
    {
        "origin_chapter": "bofm/2-ne/10",
        "noteId": "note15c",
        "content": "darkness",
        "refs": ["tg:darkness-spiritual"]
    },
    {
        "origin_chapter": "bofm/2-ne/10",
        "noteId": "note16a",
        "content": "fighteth",
        "refs": ["tg:protection-divine"]
    },
    {
        "origin_chapter": "bofm/2-ne/10",
        "noteId": "note16b",
        "content": "Zion",
        "refs": ["tg:zion"]
    },
    {
        "origin_chapter": "bofm/2-ne/10",
        "noteId": "note16c",
        "content": "shall",
        "refs": ["ot:isa:41_p11-p12#p11"]
    },
    {
        "origin_chapter": "bofm/2-ne/10",
        "noteId": "note16d",
        "content": "they",
        "refs": ["bofm:1-ne:13_p5#p5"]
    },
    {
        "origin_chapter": "bofm/2-ne/10",
        "noteId": "note16e",
        "content": "whore",
        "refs": ["tg:devil-church-of", "tg:whore"]
    },
    {
        "origin_chapter": "bofm/2-ne/10",
        "noteId": "note16f",
        "content": "they",
        "refs": ["bofm:1-ne:14_p10#p10"]
    },
    {
        "origin_chapter": "bofm/2-ne/10",
        "noteId": "note16g",
        "content": "not",
        "refs": [
            "bofm:1-ne:22_p13-p23#p13",
            "bofm:2-ne:6_p15#p15",
            "bofm:2-ne:28_p15-p32#p15",
            "bofm:3-ne:16_p8-p15#p8",
            "bofm:ether:2_p8-p11#p9"
        ]
    },
    {
        "origin_chapter": "bofm/2-ne/10",
        "noteId": "note16h",
        "content": "against",
        "refs": ["nt:matt:12_p30#p30"]
    },
    {
        "origin_chapter": "bofm/2-ne/10",
        "noteId": "note17a",
        "content": "fulfil",
        "refs": ["ot:1-kgs:8_p56#p56", "dnc:1_p38#p38", "dnc:101_p64#p64"]
    },
    {
        "origin_chapter": "bofm/2-ne/10",
        "noteId": "note17b",
        "content": "promises",
        "refs": ["tg:promise"]
    },
    {
        "origin_chapter": "bofm/2-ne/10",
        "noteId": "note18a",
        "content": "soften",
        "refs": [
            "bofm:1-ne:13_p31#p31",
            "bofm:2-ne:4_p7#p7",
            "bofm:jacob:3_p5-p9#p6",
            "bofm:hel:15_p10-p17#p12",
            "bofm:morm:5_p20-p21#p20"
        ]
    },
    {
        "origin_chapter": "bofm/2-ne/10",
        "noteId": "note18b",
        "content": "Gentiles",
        "refs": [
            "nt:matt:8_p11-p12#p11",
            "nt:matt:12_p21#p21",
            "nt:luke:13_p28-p30#p29",
            "nt:acts:10_p45#p45",
            "dnc:45_p7-p30#p9"
        ]
    },
    {
        "origin_chapter": "bofm/2-ne/10",
        "noteId": "note18c",
        "content": "blessed",
        "refs": [
            "nt:eph:3_p1-p7#p6",
            "bofm:2-ne:33_p9#p9",
            "bofm:3-ne:21_p14#p14"
        ]
    },
    {
        "origin_chapter": "bofm/2-ne/10",
        "noteId": "note18d",
        "content": "numbered",
        "refs": [
            "nt:gal:3_p7,29#p7",
            "bofm:1-ne:14_p2#p2",
            "bofm:3-ne:16_p13#p13",
            "bofm:3-ne:21_p6,22,25#p6",
            "bofm:3-ne:30_p2#p2",
            "pgp:abr:2_p9-p11#p10"
        ]
    },
    {
        "origin_chapter": "bofm/2-ne/10",
        "noteId": "note19a",
        "content": "consecrate",
        "refs": ["bofm:1-ne:13_p15#p15"]
    },
    {
        "origin_chapter": "bofm/2-ne/10",
        "noteId": "note20a",
        "content": "driven out",
        "refs": ["bofm:1-ne:1_p18-p20#p20", "bofm:1-ne:2_p1-p4#p2"]
    },
    {
        "origin_chapter": "bofm/2-ne/10",
        "noteId": "note20b",
        "content": "better land",
        "refs": ["bofm:1-ne:2_p20#p20", "tg:promised-lands"]
    },
    {
        "origin_chapter": "bofm/2-ne/10",
        "noteId": "note20c",
        "content": "path",
        "refs": ["ot:ps:8_p8#p8", "bofm:1-ne:18_p5-p23#p8"]
    },
    {
        "origin_chapter": "bofm/2-ne/10",
        "noteId": "note20d",
        "content": "isle",
        "refs": [
            "ot:isa:11_p11-p12#p11",
            "ot:isa:42_p4#p4",
            "ot:isa:51_p5#p5",
            "ot:ezek:26_p3,6-p7,15#p15",
            "ot:ezek:39_p6#p6",
            "bofm:2-ne:8_p5#p5"
        ]
    },
    {
        "origin_chapter": "bofm/2-ne/10",
        "noteId": "note21a",
        "content": "isles",
        "refs": [
            "ot:isa:49_p1#p1",
            "bofm:1-ne:19_p16#p16",
            "bofm:1-ne:21_p1#p1",
            "bofm:1-ne:22_p4#p4"
        ]
    },
    {
        "origin_chapter": "bofm/2-ne/10",
        "noteId": "note22a",
        "content": "led away",
        "refs": [
            "bofm:1-ne:22_p4-p5#p4",
            "bofm:2-ne:1_p6#p6",
            "tg:israel-scattering-of",
            "tg:israel-ten-lost-tribes-of"
        ]
    },
    {
        "origin_chapter": "bofm/2-ne/10",
        "noteId": "note23a",
        "content": "cheer up",
        "refs": ["tg:cheerful"]
    },
    {
        "origin_chapter": "bofm/2-ne/10",
        "noteId": "note23b",
        "content": "free",
        "refs": ["tg:agency"]
    },
    {
        "origin_chapter": "bofm/2-ne/10",
        "noteId": "note23c",
        "content": "act",
        "refs": ["bofm:2-ne:2_p16#p16"]
    },
    {
        "origin_chapter": "bofm/2-ne/10",
        "noteId": "note23d",
        "content": "choose",
        "refs": ["ot:deut:30_p15,19#p19"]
    },
    {
        "origin_chapter": "bofm/2-ne/10",
        "noteId": "note24a",
        "content": "reconcile",
        "refs": ["tg:reconciliation"]
    },
    {
        "origin_chapter": "bofm/2-ne/10",
        "noteId": "note24b",
        "content": "will",
        "refs": ["tg:god-will-of"]
    },
    {
        "origin_chapter": "bofm/2-ne/10",
        "noteId": "note24c",
        "content": "grace",
        "refs": ["tg:grace"]
    },
    {
        "origin_chapter": "bofm/2-ne/10",
        "noteId": "note24d",
        "content": "saved",
        "refs": ["tg:salvation", "tg:salvation-plan-of"]
    },
    {
        "origin_chapter": "bofm/2-ne/10",
        "noteId": "note25a",
        "content": "raise",
        "refs": ["tg:death-power-over", "tg:resurrection"]
    },
    {
        "origin_chapter": "bofm/2-ne/10",
        "noteId": "note25b",
        "content": "atonement",
        "refs": ["tg:jesus-christ-atonement-through"]
    },
    {
        "origin_chapter": "bofm/2-ne/10",
        "noteId": "note25c",
        "content": "eternal",
        "refs": ["tg:eternity"]
    }
]
