[
    {
        "origin_chapter": "bofm/hel/10",
        "noteId": "note2a",
        "content": "pondering",
        "refs": ["tg:meditation"]
    },
    {
        "origin_chapter": "bofm/hel/10",
        "noteId": "note3a",
        "content": "voice",
        "refs": ["tg:guidance-divine"]
    },
    {
        "origin_chapter": "bofm/hel/10",
        "noteId": "note4a",
        "content": "Blessed",
        "refs": ["nt:acts:23_p11#p11"]
    },
    {
        "origin_chapter": "bofm/hel/10",
        "noteId": "note4b",
        "content": "unwearyingness",
        "refs": [
            "nt:acts:20_p31#p31",
            "tg:dedication",
            "tg:dependability",
            "tg:priesthood-magnifying-callings-within",
            "tg:steadfastness"
        ]
    },
    {
        "origin_chapter": "bofm/hel/10",
        "noteId": "note4c",
        "content": "own life",
        "refs": ["tg:self-sacrifice"]
    },
    {
        "origin_chapter": "bofm/hel/10",
        "noteId": "note4d",
        "content": "will",
        "refs": ["bofm:mosiah:24_p15#p15", "bofm:3-ne:11_p11#p11"]
    },
    {
        "origin_chapter": "bofm/hel/10",
        "noteId": "note5a",
        "content": "all",
        "refs": ["bofm:3-ne:18_p20#p20", "dnc:88_p63-p65#p64"]
    },
    {
        "origin_chapter": "bofm/hel/10",
        "noteId": "note5b",
        "content": "done",
        "refs": ["ot:ex:33_p17#p17"]
    },
    {
        "origin_chapter": "bofm/hel/10",
        "noteId": "note5c",
        "content": "word",
        "refs": ["ot:1-kgs:17_p1#p1", "bofm:enos:1_p12#p12"]
    },
    {
        "origin_chapter": "bofm/hel/10",
        "noteId": "note5d",
        "content": "not",
        "refs": ["nt:james:4_p1-p3#p3", "bofm:2-ne:4_p35#p35", "dnc:46_p30#p30"]
    },
    {
        "origin_chapter": "bofm/hel/10",
        "noteId": "note6a",
        "content": "famine",
        "refs": ["bofm:hel:11_p4-p18#p4", "tg:drought"]
    },
    {
        "origin_chapter": "bofm/hel/10",
        "noteId": "note7a",
        "content": "power",
        "refs": ["bofm:hel:11_p18#p18"]
    },
    {
        "origin_chapter": "bofm/hel/10",
        "noteId": "note7b",
        "content": "seal",
        "refs": ["nt:matt:16_p19#p19", "tg:priesthood-authority"]
    },
    {
        "origin_chapter": "bofm/hel/10",
        "noteId": "note9a",
        "content": "mountain",
        "refs": [
            "nt:matt:17_p20#p20",
            "bofm:jacob:4_p6#p6",
            "bofm:morm:8_p24#p24",
            "bofm:ether:12_p30#p30"
        ]
    },
    {
        "origin_chapter": "bofm/hel/10",
        "noteId": "note11a",
        "content": "destruction",
        "refs": ["bofm:hel:5_p2#p2", "bofm:hel:11_p8#p8"]
    },
    {
        "origin_chapter": "bofm/hel/10",
        "noteId": "note13a",
        "content": "notwithstanding",
        "refs": ["nt:mark:6_p4-p6#p6"]
    },
    {
        "origin_chapter": "bofm/hel/10",
        "noteId": "note14a",
        "content": "smitten",
        "refs": ["bofm:hel:7_p24#p24"]
    },
    {
        "origin_chapter": "bofm/hel/10",
        "noteId": "note15a",
        "content": "revile",
        "refs": ["tg:reviling"]
    },
    {
        "origin_chapter": "bofm/hel/10",
        "noteId": "note16a",
        "content": "conveyed",
        "refs": ["nt:acts:8_p39-p40#p39"]
    }
]
